yoto_api/Card.py
yoto_api/Family.py
yoto_api/Token.py
yoto_api/YotoAPI.py
yoto_api/YotoMQTTClient.py
yoto_api/YotoManager.py
yoto_api/YotoPlayer.py
yoto_api/__init__.py
yoto_api/const.py
yoto_api/exceptions.py
yoto_api/utils.py
yoto_api-2.1.1.dist-info/licenses/AUTHORS.rst
yoto_api-2.1.1.dist-info/licenses/LICENSE
yoto_api-2.1.1.dist-info/METADATA
yoto_api-2.1.1.dist-info/WHEEL
yoto_api-2.1.1.dist-info/top_level.txt
yoto_api-2.1.1.dist-info/RECORD
