Metadata-Version: 2.4
Name: yoto_api
Version: 2.1.1
Summary: A python package that makes it a bit easier to work with the yoto play API. Not associated with Yoto in any way.
Home-page: https://github.com/cdnninja/yoto_api
Author: cdnninja
Author-email: 
License: MIT license
Keywords: yoto_api
Classifier: Development Status :: 2 - Pre-Alpha
Classifier: Intended Audience :: Developers
Classifier: License :: OSI Approved :: MIT License
Classifier: Natural Language :: English
Classifier: Programming Language :: Python :: 3.9
Requires-Python: >=3.9
License-File: LICENSE
License-File: AUTHORS.rst
Requires-Dist: pytz
Requires-Dist: requests
Requires-Dist: paho-mqtt
Dynamic: author
Dynamic: classifier
Dynamic: description
Dynamic: home-page
Dynamic: keywords
Dynamic: license
Dynamic: license-file
Dynamic: requires-dist
Dynamic: requires-python
Dynamic: summary
